builder/__init__.py
builder/main.py
builder/slave.py
builder/utils.py
builder/commands/__init__.py
builder/commands/update.py
jenkins_slave_builder-0.1.0.dist-info/DESCRIPTION.rst
jenkins_slave_builder-0.1.0.dist-info/METADATA
jenkins_slave_builder-0.1.0.dist-info/RECORD
jenkins_slave_builder-0.1.0.dist-info/WHEEL
jenkins_slave_builder-0.1.0.dist-info/entry_points.txt
jenkins_slave_builder-0.1.0.dist-info/metadata.json
jenkins_slave_builder-0.1.0.dist-info/top_level.txt
