Metadata-Version: 2.0
Name: jenkins-slave-builder
Version: 0.1.0
Summary: Build jenkins slaves in YAML
Home-page: https://github.com/masaki/jenkins-slave-builder
Author: ikasam_a
Author-email: masaki.nakagawa@gmail.com
License: UNKNOWN
Platform: Any
Requires-Dist: PyYAML
Requires-Dist: argparse
Requires-Dist: cliff
Requires-Dist: requests
